lti_consumer/__init__.py
lti_consumer/admin.py
lti_consumer/api.py
lti_consumer/apps.py
lti_consumer/data.py
lti_consumer/exceptions.py
lti_consumer/filters.py
lti_consumer/forms.py
lti_consumer/lti_xblock.py
lti_consumer/models.py
lti_consumer/outcomes.py
lti_consumer/track.py
lti_consumer/utils.py
lti_consumer/lti_1p1/__init__.py
lti_consumer/lti_1p1/consumer.py
lti_consumer/lti_1p1/exceptions.py
lti_consumer/lti_1p1/oauth.py
lti_consumer/lti_1p1/contrib/__init__.py
lti_consumer/lti_1p1/contrib/django.py
lti_consumer/lti_1p1/contrib/tests/__init__.py
lti_consumer/lti_1p1/contrib/tests/test_django.py
lti_consumer/lti_1p1/tests/__init__.py
lti_consumer/lti_1p1/tests/test_consumer.py
lti_consumer/lti_1p1/tests/test_oauth.py
lti_consumer/lti_1p3/__init__.py
lti_consumer/lti_1p3/ags.py
lti_consumer/lti_1p3/constants.py
lti_consumer/lti_1p3/consumer.py
lti_consumer/lti_1p3/deep_linking.py
lti_consumer/lti_1p3/exceptions.py
lti_consumer/lti_1p3/key_handlers.py
lti_consumer/lti_1p3/nprs.py
lti_consumer/lti_1p3/extensions/__init__.py
lti_consumer/lti_1p3/extensions/rest_framework/__init__.py
lti_consumer/lti_1p3/extensions/rest_framework/authentication.py
lti_consumer/lti_1p3/extensions/rest_framework/constants.py
lti_consumer/lti_1p3/extensions/rest_framework/parsers.py
lti_consumer/lti_1p3/extensions/rest_framework/permissions.py
lti_consumer/lti_1p3/extensions/rest_framework/renderers.py
lti_consumer/lti_1p3/extensions/rest_framework/serializers.py
lti_consumer/lti_1p3/extensions/rest_framework/utils.py
lti_consumer/lti_1p3/tests/__init__.py
lti_consumer/lti_1p3/tests/test_ags.py
lti_consumer/lti_1p3/tests/test_consumer.py
lti_consumer/lti_1p3/tests/test_deep_linking.py
lti_consumer/lti_1p3/tests/test_key_handlers.py
lti_consumer/lti_1p3/tests/test_nrps.py
lti_consumer/lti_1p3/tests/utils.py
lti_consumer/lti_1p3/tests/extensions/__init__.py
lti_consumer/lti_1p3/tests/extensions/rest_framework/__init__.py
lti_consumer_xblock-9.14.3.dist-info/licenses/LICENSE
lti_consumer_xblock-9.14.3.dist-info/licenses/NOTICE
lti_consumer_xblock-9.14.3.dist-info/METADATA
lti_consumer_xblock-9.14.3.dist-info/WHEEL
lti_consumer_xblock-9.14.3.dist-info/dependency_links.txt
lti_consumer_xblock-9.14.3.dist-info/entry_points.txt
lti_consumer_xblock-9.14.3.dist-info/top_level.txt
lti_consumer_xblock-9.14.3.dist-info/RECORD
