Metadata-Version: 2.4
Name: lti-consumer-xblock
Version: 9.14.3
Summary: This XBlock implements the consumer side of the LTI specification.
Home-page: https://github.com/openedx/xblock-lti-consumer
Author: Open edX project
Author-email: oscm@edx.org
Keywords: lti consumer xblock
Classifier: Development Status :: 5 - Production/Stable
Classifier: Framework :: Django
Classifier: Framework :: Django :: 3.2
Classifier: Framework :: Django :: 4.0
Classifier: Framework :: Django :: 5.2
Classifier: Intended Audience :: Developers
Classifier: License :: OSI Approved :: GNU Affero General Public License v3
Classifier: Natural Language :: English
Classifier: Programming Language :: Python :: 3
Classifier: Programming Language :: Python :: 3.11
Classifier: Programming Language :: Python :: 3.12
License-File: LICENSE
License-File: NOTICE
Requires-Dist: XBlock
Requires-Dist: attrs
Requires-Dist: bleach>=6.0.0
Requires-Dist: django
Requires-Dist: django-config-models
Requires-Dist: django-filter
Requires-Dist: django-statici18n
Requires-Dist: edx-ccx-keys
Requires-Dist: edx-opaque-keys
Requires-Dist: jsonfield
Requires-Dist: lazy
Requires-Dist: lxml
Requires-Dist: mako
Requires-Dist: oauthlib
Requires-Dist: openedx-django-pyfs
Requires-Dist: openedx-filters
Requires-Dist: pycryptodomex
Requires-Dist: pyjwt
Dynamic: author
Dynamic: author-email
Dynamic: classifier
Dynamic: description
Dynamic: description-content-type
Dynamic: home-page
Dynamic: keywords
Dynamic: license-file
Dynamic: requires-dist
Dynamic: summary
